dpmmpython/__init__.py
dpmmpython/dpmmwrapper.py
dpmmpython/install.py
dpmmpython/priors.py
dpmmpython/release.py
dpmmpython-0.1.10.dist-info/LICENSE
dpmmpython-0.1.10.dist-info/METADATA
dpmmpython-0.1.10.dist-info/WHEEL
dpmmpython-0.1.10.dist-info/top_level.txt
dpmmpython-0.1.10.dist-info/RECORD
