Metadata-Version: 2.1
Name: dpmmpython
Version: 0.1.10
Summary: Python wrapper for DPMMSubClusters julia package
Home-page: https://github.com/BGU-CS-VIL/DPMMPython
Author: Or Dinari
Author-email: dinari@post.bgu.ac.il
License: MIT
Project-URL: Source, https://github.com/BGU-CS-VIL/DPMMPython
Project-URL: Tracker, https://github.com/BGU-CS-VIL/issues
Project-URL: Documentation, https://bgu-cs-vil.github.io/DPMMSubClusters.jl/latest/
Keywords: julia python
Classifier: Development Status :: 3 - Alpha
Classifier: License :: OSI Approved :: MIT License
Classifier: Programming Language :: Python :: 2
Classifier: Programming Language :: Python :: 2.7
Classifier: Programming Language :: Python :: 3
Classifier: Programming Language :: Python :: 3.4
Classifier: Programming Language :: Python :: 3.5
Classifier: Programming Language :: Python :: 3.6
Classifier: Programming Language :: Python :: 3.7
License-File: LICENSE
Requires-Dist: julia
Requires-Dist: wget
Provides-Extra: test
Requires-Dist: numpy ; extra == 'test'
Requires-Dist: ipython ; extra == 'test'
Requires-Dist: pytest (>=4.4) ; extra == 'test'
Requires-Dist: mock ; extra == 'test'
